remla2024_team9_lib_ml/__init__.py
remla2024_team9_lib_ml/data_split.py
remla2024_team9_lib_ml/encode_labels.py
remla2024_team9_lib_ml/tokenize_features.py
remla2024_team9_lib_ml-0.1.1.dist-info/METADATA
remla2024_team9_lib_ml-0.1.1.dist-info/WHEEL
remla2024_team9_lib_ml-0.1.1.dist-info/RECORD
